[{"name":"Tachiyomi: Komiktap","pkg":"eu.kanade.tachiyomi.extension.id.komiktap","apk":"tachiyomi-id.komiktap-v1.4.34.apk","lang":"id","code":1,"version":"1.4.34","nsfw":0,"sources":[]},{"name":"Tachiyomi: Holotoon","pkg":"eu.kanade.tachiyomi.extension.id.holotoon","apk":"tachiyomi-id.holotoon-v1.4.45.apk","lang":"id","code":1,"version":"1.4.45","nsfw":0,"sources":[]},{"name":"Tachiyomi: Komikindoco","pkg":"eu.kanade.tachiyomi.extension.id.komikindoco","apk":"tachiyomi-id.komikindoco-v1.4.35.apk","lang":"id","code":1,"version":"1.4.35","nsfw":0,"sources":[]},{"name":"Tachiyomi: Lepoytl","pkg":"eu.kanade.tachiyomi.extension.id.lepoytl","apk":"tachiyomi-id.lepoytl-v1.4.11.apk","lang":"id","code":1,"version":"1.4.11","nsfw":0,"sources":[]},{"name":"Tachiyomi: Onepieceberwarna","pkg":"eu.kanade.tachiyomi.extension.id.onepieceberwarna","apk":"tachiyomi-id.onepieceberwarna-v1.4.1.apk","lang":"id","code":1,"version":"1.4.1","nsfw":0,"sources":[]},{"name":"Tachiyomi: Hwago","pkg":"eu.kanade.tachiyomi.extension.id.hwago","apk":"tachiyomi-id.hwago-v1.4.48.apk","lang":"id","code":1,"version":"1.4.48","nsfw":0,"sources":[]},{"name":"Tachiyomi: Shirakami","pkg":"eu.kanade.tachiyomi.extension.id.shirakami","apk":"tachiyomi-id.shirakami-v1.4.30.apk","lang":"id","code":1,"version":"1.4.30","nsfw":0,"sources":[]},{"name":"Tachiyomi: Manhwalandmom","pkg":"eu.kanade.tachiyomi.extension.id.manhwalandmom","apk":"tachiyomi-id.manhwalandmom-v1.4.39.apk","lang":"id","code":1,"version":"1.4.39","nsfw":0,"sources":[]},{"name":"Tachiyomi: Medusascans","pkg":"eu.kanade.tachiyomi.extension.id.medusascans","apk":"tachiyomi-id.medusascans-v1.4.1.apk","lang":"id","code":1,"version":"1.4.1","nsfw":0,"sources":[]},{"name":"Tachiyomi: Shirodoujin","pkg":"eu.kanade.tachiyomi.extension.id.shirodoujin","apk":"tachiyomi-id.shirodoujin-v1.4.2.apk","lang":"id","code":1,"version":"1.4.2","nsfw":0,"sources":[]},{"name":"Tachiyomi: Manhwalistorg","pkg":"eu.kanade.tachiyomi.extension.id.manhwalistorg","apk":"tachiyomi-id.manhwalistorg-v1.4.31.apk","lang":"id","code":1,"version":"1.4.31","nsfw":0,"sources":[]},{"name":"Tachiyomi: Kumopoi","pkg":"eu.kanade.tachiyomi.extension.id.kumopoi","apk":"tachiyomi-id.kumopoi-v1.4.30.apk","lang":"id","code":1,"version":"1.4.30","nsfw":0,"sources":[]},{"name":"Tachiyomi: Manhwadesu","pkg":"eu.kanade.tachiyomi.extension.id.manhwadesu","apk":"tachiyomi-id.manhwadesu-v1.4.39.apk","lang":"id","code":1,"version":"1.4.39","nsfw":0,"sources":[]},{"name":"Tachiyomi: Ngamenkomik","pkg":"eu.kanade.tachiyomi.extension.id.ngamenkomik","apk":"tachiyomi-id.ngamenkomik-v1.4.11.apk","lang":"id","code":1,"version":"1.4.11","nsfw":0,"sources":[]},{"name":"Tachiyomi: Kiryuu","pkg":"eu.kanade.tachiyomi.extension.id.kiryuu","apk":"tachiyomi-id.kiryuu-v1.4.46.apk","lang":"id","code":1,"version":"1.4.46","nsfw":0,"sources":[]},{"name":"Tachiyomi: Cosmicscansid","pkg":"eu.kanade.tachiyomi.extension.id.cosmicscansid","apk":"tachiyomi-id.cosmicscansid-v1.4.45.apk","lang":"id","code":1,"version":"1.4.45","nsfw":0,"sources":[]},{"name":"Tachiyomi: Komikav","pkg":"eu.kanade.tachiyomi.extension.id.komikav","apk":"tachiyomi-id.komikav-v1.4.32.apk","lang":"id","code":1,"version":"1.4.32","nsfw":0,"sources":[]},{"name":"Tachiyomi: Crotpedia","pkg":"eu.kanade.tachiyomi.extension.id.crotpedia","apk":"tachiyomi-id.crotpedia-v1.4.1.apk","lang":"id","code":1,"version":"1.4.1","nsfw":0,"sources":[]},{"name":"Tachiyomi: Doujindesu","pkg":"eu.kanade.tachiyomi.extension.id.doujindesu","apk":"tachiyomi-id.doujindesu-v1.4.11.apk","lang":"id","code":1,"version":"1.4.11","nsfw":0,"sources":[]},{"name":"Tachiyomi: Maidmanga","pkg":"eu.kanade.tachiyomi.extension.id.maidmanga","apk":"tachiyomi-id.maidmanga-v1.4.11.apk","lang":"id","code":1,"version":"1.4.11","nsfw":0,"sources":[]},{"name":"Tachiyomi: Mangkomik","pkg":"eu.kanade.tachiyomi.extension.id.mangkomik","apk":"tachiyomi-id.mangkomik-v1.4.39.apk","lang":"id","code":1,"version":"1.4.39","nsfw":0,"sources":[]},{"name":"Tachiyomi: Mangatale","pkg":"eu.kanade.tachiyomi.extension.id.mangatale","apk":"tachiyomi-id.mangatale-v1.4.44.apk","lang":"id","code":1,"version":"1.4.44","nsfw":0,"sources":[]},{"name":"Tachiyomi: Mangasusu","pkg":"eu.kanade.tachiyomi.extension.id.mangasusu","apk":"tachiyomi-id.mangasusu-v1.4.35.apk","lang":"id","code":1,"version":"1.4.35","nsfw":0,"sources":[]},{"name":"Tachiyomi: Natsu","pkg":"eu.kanade.tachiyomi.extension.id.natsu","apk":"tachiyomi-id.natsu-v1.4.31.apk","lang":"id","code":1,"version":"1.4.31","nsfw":0,"sources":[]},{"name":"Tachiyomi: Themanga","pkg":"eu.kanade.tachiyomi.extension.id.themanga","apk":"tachiyomi-id.themanga-v1.4.45.apk","lang":"id","code":1,"version":"1.4.45","nsfw":0,"sources":[]},{"name":"Tachiyomi: Florascans","pkg":"eu.kanade.tachiyomi.extension.id.florascans","apk":"tachiyomi-id.florascans-v1.4.30.apk","lang":"id","code":1,"version":"1.4.30","nsfw":0,"sources":[]},{"name":"Tachiyomi: Komikucom","pkg":"eu.kanade.tachiyomi.extension.id.komikucom","apk":"tachiyomi-id.komikucom-v1.4.32.apk","lang":"id","code":1,"version":"1.4.32","nsfw":0,"sources":[]},{"name":"Tachiyomi: Mikoroku","pkg":"eu.kanade.tachiyomi.extension.id.mikoroku","apk":"tachiyomi-id.mikoroku-v1.4.14.apk","lang":"id","code":1,"version":"1.4.14","nsfw":0,"sources":[]},{"name":"Tachiyomi: Mangalay","pkg":"eu.kanade.tachiyomi.extension.id.mangalay","apk":"tachiyomi-id.mangalay-v1.4.1.apk","lang":"id","code":1,"version":"1.4.1","nsfw":0,"sources":[]},{"name":"Tachiyomi: Birdtoon","pkg":"eu.kanade.tachiyomi.extension.id.birdtoon","apk":"tachiyomi-id.birdtoon-v1.4.47.apk","lang":"id","code":1,"version":"1.4.47","nsfw":0,"sources":[]},{"name":"Tachiyomi: Inazumanga","pkg":"eu.kanade.tachiyomi.extension.id.inazumanga","apk":"tachiyomi-id.inazumanga-v1.4.37.apk","lang":"id","code":1,"version":"1.4.37","nsfw":0,"sources":[]},{"name":"Tachiyomi: Roseveil","pkg":"eu.kanade.tachiyomi.extension.id.roseveil","apk":"tachiyomi-id.roseveil-v1.4.45.apk","lang":"id","code":1,"version":"1.4.45","nsfw":0,"sources":[]},{"name":"Tachiyomi: Sektedoujin","pkg":"eu.kanade.tachiyomi.extension.id.sektedoujin","apk":"tachiyomi-id.sektedoujin-v1.4.35.apk","lang":"id","code":1,"version":"1.4.35","nsfw":0,"sources":[]},{"name":"Tachiyomi: Softkomik","pkg":"eu.kanade.tachiyomi.extension.id.softkomik","apk":"tachiyomi-id.softkomik-v1.4.1.apk","lang":"id","code":1,"version":"1.4.1","nsfw":0,"sources":[]},{"name":"Tachiyomi: Neumanga","pkg":"eu.kanade.tachiyomi.extension.id.neumanga","apk":"tachiyomi-id.neumanga-v1.4.2.apk","lang":"id","code":1,"version":"1.4.2","nsfw":0,"sources":[]},{"name":"Tachiyomi: Comicazen","pkg":"eu.kanade.tachiyomi.extension.id.comicazen","apk":"tachiyomi-id.comicazen-v1.4.1.apk","lang":"id","code":1,"version":"1.4.1","nsfw":0,"sources":[]},{"name":"Tachiyomi: Bacakomik","pkg":"eu.kanade.tachiyomi.extension.id.bacakomik","apk":"tachiyomi-id.bacakomik-v1.4.13.apk","lang":"id","code":1,"version":"1.4.13","nsfw":0,"sources":[]},{"name":"Tachiyomi: Shinigami","pkg":"eu.kanade.tachiyomi.extension.id.shinigami","apk":"tachiyomi-id.shinigami-v1.4.76.apk","lang":"id","code":1,"version":"1.4.76","nsfw":0,"sources":[]},{"name":"Tachiyomi: Komikindo","pkg":"eu.kanade.tachiyomi.extension.id.komikindo","apk":"tachiyomi-id.komikindo-v1.4.32.apk","lang":"id","code":1,"version":"1.4.32","nsfw":0,"sources":[]},{"name":"Tachiyomi: Tooncubus","pkg":"eu.kanade.tachiyomi.extension.id.tooncubus","apk":"tachiyomi-id.tooncubus-v1.4.11.apk","lang":"id","code":1,"version":"1.4.11","nsfw":0,"sources":[]},{"name":"Tachiyomi: Luvyaa","pkg":"eu.kanade.tachiyomi.extension.id.Luvyaa","apk":"tachiyomi-id.Luvyaa-v1.4.30.apk","lang":"id","code":1,"version":"1.4.30","nsfw":0,"sources":[]},{"name":"Tachiyomi: Kumapoi","pkg":"eu.kanade.tachiyomi.extension.id.kumapoi","apk":"tachiyomi-id.kumapoi-v1.4.33.apk","lang":"id","code":1,"version":"1.4.33","nsfw":0,"sources":[]},{"name":"Tachiyomi: Kanzenin","pkg":"eu.kanade.tachiyomi.extension.id.kanzenin","apk":"tachiyomi-id.kanzenin-v1.4.31.apk","lang":"id","code":1,"version":"1.4.31","nsfw":0,"sources":[]},{"name":"Tachiyomi: Mangacan","pkg":"eu.kanade.tachiyomi.extension.id.mangacan","apk":"tachiyomi-id.mangacan-v1.4.30.apk","lang":"id","code":1,"version":"1.4.30","nsfw":0,"sources":[]},{"name":"Tachiyomi: Mgkomik","pkg":"eu.kanade.tachiyomi.extension.id.mgkomik","apk":"tachiyomi-id.mgkomik-v1.4.63.apk","lang":"id","code":1,"version":"1.4.63","nsfw":0,"sources":[]},{"name":"Tachiyomi: Ainzscansid","pkg":"eu.kanade.tachiyomi.extension.id.ainzscansid","apk":"tachiyomi-id.ainzscansid-v1.4.32.apk","lang":"id","code":1,"version":"1.4.32","nsfw":0,"sources":[]},{"name":"Tachiyomi: Bacami","pkg":"eu.kanade.tachiyomi.extension.id.bacami","apk":"tachiyomi-id.bacami-v1.4.1.apk","lang":"id","code":1,"version":"1.4.1","nsfw":0,"sources":[]},{"name":"Tachiyomi: Komikgo","pkg":"eu.kanade.tachiyomi.extension.id.komikgo","apk":"tachiyomi-id.komikgo-v1.4.30.apk","lang":"id","code":1,"version":"1.4.30","nsfw":0,"sources":[]},{"name":"Tachiyomi: Komikdewasa","pkg":"eu.kanade.tachiyomi.extension.id.komikdewasa","apk":"tachiyomi-id.komikdewasa-v1.4.30.apk","lang":"id","code":1,"version":"1.4.30","nsfw":0,"sources":[]},{"name":"Tachiyomi: Izanamiscans","pkg":"eu.kanade.tachiyomi.extension.id.izanamiscans","apk":"tachiyomi-id.izanamiscans-v1.4.30.apk","lang":"id","code":1,"version":"1.4.30","nsfw":0,"sources":[]},{"name":"Tachiyomi: Aarlas","pkg":"eu.kanade.tachiyomi.extension.id.aarlas","apk":"tachiyomi-id.aarlas-v1.4.11.apk","lang":"id","code":1,"version":"1.4.11","nsfw":0,"sources":[]},{"name":"Tachiyomi: Soulscans","pkg":"eu.kanade.tachiyomi.extension.id.soulscans","apk":"tachiyomi-id.soulscans-v1.4.32.apk","lang":"id","code":1,"version":"1.4.32","nsfw":0,"sources":[]},{"name":"Tachiyomi: Otascans","pkg":"eu.kanade.tachiyomi.extension.id.otascans","apk":"tachiyomi-id.otascans-v1.4.31.apk","lang":"id","code":1,"version":"1.4.31","nsfw":0,"sources":[]},{"name":"Tachiyomi: Lumoskomik","pkg":"eu.kanade.tachiyomi.extension.id.lumoskomik","apk":"tachiyomi-id.lumoskomik-v1.4.48.apk","lang":"id","code":1,"version":"1.4.48","nsfw":0,"sources":[]},{"name":"Tachiyomi: Manhwaindo","pkg":"eu.kanade.tachiyomi.extension.id.manhwaindo","apk":"tachiyomi-id.manhwaindo-v1.4.37.apk","lang":"id","code":1,"version":"1.4.37","nsfw":0,"sources":[]},{"name":"Tachiyomi: Sasangeyou","pkg":"eu.kanade.tachiyomi.extension.id.sasangeyou","apk":"tachiyomi-id.sasangeyou-v1.4.30.apk","lang":"id","code":1,"version":"1.4.30","nsfw":0,"sources":[]},{"name":"Tachiyomi: Komikzoid","pkg":"eu.kanade.tachiyomi.extension.id.komikzoid","apk":"tachiyomi-id.komikzoid-v1.4.1.apk","lang":"id","code":1,"version":"1.4.1","nsfw":0,"sources":[]},{"name":"Tachiyomi: Doujinku","pkg":"eu.kanade.tachiyomi.extension.id.doujinku","apk":"tachiyomi-id.doujinku-v1.4.33.apk","lang":"id","code":1,"version":"1.4.33","nsfw":0,"sources":[]},{"name":"Tachiyomi: Pramramadhan","pkg":"eu.kanade.tachiyomi.extension.id.pramramadhan","apk":"tachiyomi-id.pramramadhan-v1.4.1.apk","lang":"id","code":1,"version":"1.4.1","nsfw":0,"sources":[]},{"name":"Tachiyomi: Futari","pkg":"eu.kanade.tachiyomi.extension.id.futari","apk":"tachiyomi-id.futari-v1.4.30.apk","lang":"id","code":1,"version":"1.4.30","nsfw":0,"sources":[]},{"name":"Tachiyomi: Manhwalistid","pkg":"eu.kanade.tachiyomi.extension.id.manhwalistid","apk":"tachiyomi-id.manhwalistid-v1.4.35.apk","lang":"id","code":1,"version":"1.4.35","nsfw":0,"sources":[]},{"name":"Tachiyomi: Komikstation","pkg":"eu.kanade.tachiyomi.extension.id.komikstation","apk":"tachiyomi-id.komikstation-v1.4.36.apk","lang":"id","code":1,"version":"1.4.36","nsfw":0,"sources":[]},{"name":"Tachiyomi: Klmanhua","pkg":"eu.kanade.tachiyomi.extension.id.klmanhua","apk":"tachiyomi-id.klmanhua-v1.4.11.apk","lang":"id","code":1,"version":"1.4.11","nsfw":0,"sources":[]},{"name":"Tachiyomi: Siimanga","pkg":"eu.kanade.tachiyomi.extension.id.siimanga","apk":"tachiyomi-id.siimanga-v1.4.45.apk","lang":"id","code":1,"version":"1.4.45","nsfw":0,"sources":[]},{"name":"Tachiyomi: Lumireverse","pkg":"eu.kanade.tachiyomi.extension.id.lumireverse","apk":"tachiyomi-id.lumireverse-v1.4.45.apk","lang":"id","code":1,"version":"1.4.45","nsfw":0,"sources":[]},{"name":"Tachiyomi: Klikmanga","pkg":"eu.kanade.tachiyomi.extension.id.klikmanga","apk":"tachiyomi-id.klikmanga-v1.4.49.apk","lang":"id","code":1,"version":"1.4.49","nsfw":0,"sources":[]},{"name":"Tachiyomi: Noromax","pkg":"eu.kanade.tachiyomi.extension.id.noromax","apk":"tachiyomi-id.noromax-v1.4.32.apk","lang":"id","code":1,"version":"1.4.32","nsfw":0,"sources":[]},{"name":"Tachiyomi: Dreamteamsscans","pkg":"eu.kanade.tachiyomi.extension.id.dreamteamsscans","apk":"tachiyomi-id.dreamteamsscans-v1.4.30.apk","lang":"id","code":1,"version":"1.4.30","nsfw":0,"sources":[]},{"name":"Tachiyomi: Ngomik","pkg":"eu.kanade.tachiyomi.extension.id.ngomik","apk":"tachiyomi-id.ngomik-v1.4.34.apk","lang":"id","code":1,"version":"1.4.34","nsfw":0,"sources":[]},{"name":"Tachiyomi: Komikindoid","pkg":"eu.kanade.tachiyomi.extension.id.komikindoid","apk":"tachiyomi-id.komikindoid-v1.4.18.apk","lang":"id","code":1,"version":"1.4.18","nsfw":0,"sources":[]},{"name":"Tachiyomi: Westmanga","pkg":"eu.kanade.tachiyomi.extension.id.westmanga","apk":"tachiyomi-id.westmanga-v1.4.38.apk","lang":"id","code":1,"version":"1.4.38","nsfw":0,"sources":[]},{"name":"Tachiyomi: Pornhwa18","pkg":"eu.kanade.tachiyomi.extension.id.pornhwa18","apk":"tachiyomi-id.pornhwa18-v1.4.45.apk","lang":"id","code":1,"version":"1.4.45","nsfw":0,"sources":[]},{"name":"Tachiyomi: Mihentai","pkg":"eu.kanade.tachiyomi.extension.id.mihentai","apk":"tachiyomi-id.mihentai-v1.4.33.apk","lang":"id","code":1,"version":"1.4.33","nsfw":0,"sources":[]},{"name":"Tachiyomi: Nimemob","pkg":"eu.kanade.tachiyomi.extension.id.nimemob","apk":"tachiyomi-id.nimemob-v1.4.11.apk","lang":"id","code":1,"version":"1.4.11","nsfw":0,"sources":[]},{"name":"Tachiyomi: Manhwahana","pkg":"eu.kanade.tachiyomi.extension.id.manhwahana","apk":"tachiyomi-id.manhwahana-v1.4.45.apk","lang":"id","code":1,"version":"1.4.45","nsfw":0,"sources":[]},{"name":"Tachiyomi: Mangakita","pkg":"eu.kanade.tachiyomi.extension.id.mangakita","apk":"tachiyomi-id.mangakita-v1.4.32.apk","lang":"id","code":1,"version":"1.4.32","nsfw":0,"sources":[]},{"name":"Tachiyomi: Komiku","pkg":"eu.kanade.tachiyomi.extension.id.komiku","apk":"tachiyomi-id.komiku-v1.4.19.apk","lang":"id","code":1,"version":"1.4.19","nsfw":0,"sources":[]},{"name":"Tachiyomi: Sektekomik","pkg":"eu.kanade.tachiyomi.extension.id.sektekomik","apk":"tachiyomi-id.sektekomik-v1.4.27.apk","lang":"id","code":1,"version":"1.4.27","nsfw":0,"sources":[]},{"name":"Tachiyomi: Monzeekomik","pkg":"eu.kanade.tachiyomi.extension.id.monzeekomik","apk":"tachiyomi-id.monzeekomik-v1.4.31.apk","lang":"id","code":1,"version":"1.4.31","nsfw":0,"sources":[]},{"name":"Tachiyomi: Komikcast","pkg":"eu.kanade.tachiyomi.extension.id.komikcast","apk":"tachiyomi-id.komikcast-v1.4.75.apk","lang":"id","code":1,"version":"1.4.75","nsfw":0,"sources":[]},{"name":"Tachiyomi: Yubikiri","pkg":"eu.kanade.tachiyomi.extension.id.yubikiri","apk":"tachiyomi-id.yubikiri-v1.4.46.apk","lang":"id","code":1,"version":"1.4.46","nsfw":0,"sources":[]},{"name":"Tachiyomi: Dojingnet","pkg":"eu.kanade.tachiyomi.extension.id.dojingnet","apk":"tachiyomi-id.dojingnet-v1.4.30.apk","lang":"id","code":1,"version":"1.4.30","nsfw":0,"sources":[]},{"name":"Tachiyomi: Shiyurasub","pkg":"eu.kanade.tachiyomi.extension.id.shiyurasub","apk":"tachiyomi-id.shiyurasub-v1.4.11.apk","lang":"id","code":1,"version":"1.4.11","nsfw":0,"sources":[]},{"name":"Tachiyomi: Lianscans","pkg":"eu.kanade.tachiyomi.extension.id.lianscans","apk":"tachiyomi-id.lianscans-v1.4.31.apk","lang":"id","code":1,"version":"1.4.31","nsfw":0,"sources":[]}]